plotboss/__init__.py
plotboss/__main__.py
plotboss/job.py
plotboss/plotboss.py
plotboss/plotlog.py
plotboss/plotview.py
plotboss/settings.toml
plotboss/tail.py
plotboss/utils.py
plotboss-0.3.0.dist-info/LICENSE
plotboss-0.3.0.dist-info/METADATA
plotboss-0.3.0.dist-info/WHEEL
plotboss-0.3.0.dist-info/entry_points.txt
plotboss-0.3.0.dist-info/top_level.txt
plotboss-0.3.0.dist-info/RECORD
