Metadata-Version: 2.1
Name: plotboss
Version: 0.3.0
Summary: Chia network plot manager, auto plot manager, plot like a boss
Home-page: https://github.com/zeaphoo/plotboss/
Author: Wei Zhuo
Author-email: zeaphoo@qq.com
License: MIT
Platform: any
Classifier: Development Status :: 4 - Beta
Classifier: Environment :: Console
Classifier: Intended Audience :: Developers
Classifier: License :: OSI Approved :: MIT License
Classifier: Operating System :: Microsoft :: Windows :: Windows 10
Classifier: Programming Language :: Python
Classifier: Programming Language :: Python :: 3
Classifier: Programming Language :: Python :: 3.7
Classifier: Programming Language :: Python :: 3.8
Classifier: Programming Language :: Python :: 3.9
Requires-Python: >=3.7
Requires-Dist: basepy (>=0.3.5)
Requires-Dist: psutil
Requires-Dist: pendulum
Requires-Dist: asciimatics
Requires-Dist: loguru
Provides-Extra: test
Requires-Dist: pytest (>=3) ; extra == 'test'
